[
    {
        "title": "招聘老外学汉语教师",
        "content": "要求：1、具有中国语言资源开发中心颁发的对外汉语教师研修合格证的同学优先。<br>&nbsp;&nbsp;&nbsp;&nbsp;&nbsp;&nbsp;&nbsp;&nbsp;&nbsp;&nbsp;&nbsp;&nbsp;2、具有一定的对外汉语教学经验的同学优先。<br>联系电话：15190283068<br>地址：百脑汇科技大厦12楼1209&nbsp;学府教育<br><a target='_blank' href='http://www.xuefuedu.com'>http://www.xuefuedu.com</a>",

        "time": "2013-11-3",
        "size":"1",
        "tag": ""
    },
    {
        "title": "招网站编辑，800元/月",
        "content": "工作内容：每天整理发布三篇短文<br>工作要求：时间充足，有很强的文字功底，文艺青年就更好了<br>工作时间：自由<br>工作地点：自由<br>有意者请发送简历至914245986@qq.com<br>(附上相关作品或者豆瓣、人人、微博等能体现你文字功底的地址)",

        "time": "2013-11-3",
        "size":"2",        
        "tag": ""
    },

    {
        "title": "招聘四六级实习教师",
        "content": "招聘四六级教师招聘四六级教师<br>要求：在校研究生，有一定教学经验，上课时间6:30-8:30<br>电话15190283068<br>地址百脑汇科技大厦12楼<br>一对一授课<br>QQ:67477948",

        "time": "2013-11-3",
        "size":"1",        
        "tag": ""
    },
    
    {
        "title": "A21家教招聘信息",
        "content": "辅导课目：高二女生的数、理、化三科；&nbsp;<br>&nbsp;辅导时间：寒假期间，具体时间可协商<br>&nbsp;上课地点：江南大学<br>&nbsp;招聘要求：女生，数理化成绩优异啊，大一年级学生优先，有经验者优先。&nbsp;&nbsp;<br>&nbsp;有意者请到北活一楼F107勤工助学办公室咨询报名。&nbsp;",

        "time": "2013-11-3",
        "size":"2",        
        "tag": ""
    },
    
    {
        "title": "暑期兼职：无锡首届青岛啤酒节招募有偿志愿者（工作时间7月27日-8月12日）",
        "content": "附件: <a href='/attachments/2012/05/10/13366448423070.xlsx'>13366448423070.xlsx</a>附件: <a href='/attachments/2012/05/10/13366448217598.docx'>13366448217598.docx</a>&nbsp;<br><b>&nbsp;<br><br><span style='font-size:24px;'><span style='font-size:10.5pt;'>一、报名要求：&nbsp;</span></span></b><br><br>1．自愿参加首届无锡青岛啤酒节有偿志愿服务工作；<br><br>2．年龄要求：全日制在校大学生；<br><br>3．遵守中华人民共和国法律、法规；<br><br>4．能够参加啤酒节运营前期的培训及相关活动；<br><br>5．具备志愿服务岗位必需的知识和技能；<br><br>6．身体健康，能满足相应志愿者岗位工作要求。<br><br><b><span style='font-size:24px;'><span style='font-size:10.5pt;'>二、权利及义务&nbsp;</span></span></b><br><br>（一）权利<br><br>1．了解中国无锡首届青岛啤酒节志愿者工作政策；<br><br>2．在岗位确定之前表达对服务岗位的意愿；<br><br>3．获得与所从事的啤酒节志愿服务活动相关的必要条件或者保障；<br><br>4．参加志愿者评比表彰；<br><br>5．获得志愿者服务证明；<br><br>6．对志愿者工作提出意见和建议；<br><br>7．申请退出志愿服务。<br><br>（二）义务<br><br>1．遵守中华人民共和国法律法规和啤酒节组委会制定的相关规定；<br><br>2．履行经本人签署的志愿服务承诺；<br><br>3．参加啤酒节组委会统一安排的选拔、培训和相关活动；<br><br>4．服从组委会的指挥和调配，服从所在团队的管理，确保规定的岗位最少服务时间；<br><br>5．遵守相关工作的保密制度；<br><br>6．因特殊原因需提前退出志愿者工作岗位的，应提前三天以书面形式向组委会志愿者管理机构提出申请，征得同意后方可退出；<br><br>7．珍惜和维护中国无锡首届青岛啤酒节的声誉，不得利用志愿者身份从事与啤酒节志愿服务活动宗旨、目的不符的行为。<br><br><b><span style='font-size:24px;'><span style='font-size:10.5pt;'>三、招募具体安排&nbsp;</span></span></b><br><br>（一）报名地点：北活F107<br><br><span style='color:black;'>&nbsp;(</span><span style='color:black;'>二）报名时间及日程安排：</span>&nbsp;<br><br><span style='color:black;'>报名时间：2012年5月11日至2012年5月25日。&nbsp;</span><br><br><span style='color:black;'>人员筛选：6月4日到6月8日</span>&nbsp;<br><br><span style='color:black;'>培训日期：预计在7月23日-7月26日</span>&nbsp;<br><br>（三）招募流程<br><br>1．无锡啤酒节志愿者的招募流程主要包括申请人报名、材料审核、选拔、岗位分配、发出录用通知等。<br><br>2．按照岗位要求分批次录用无锡啤酒节志愿者。<br><br>（四）志愿者的培训<br><br><b>&nbsp;</b>&nbsp;<br><br>1.培训内容：<br><br>岗位服务细则是对2012年无锡首届青岛啤酒节期间志愿者服务工作的全面介绍，培训对象为志愿者。志愿者作为啤酒节的重要组成部分将在不同的岗位上全面开展工作，如现场咨询、园区播音、现场服务等等。岗位服务细则培训将针对服务工作特点，对工作地点、任务、工作职责、运行规范、注意事项等提供详细的指导。&nbsp;<br><br>2.培训地点：<br><br>江南大学学生活动中心F105<br><br><b><span style='font-size:24px;'><span style='font-size:10.5pt;'>四、工作时间&nbsp;：</span><span style='font-size:10.5pt;'>7</span><span style='font-size:10.5pt;'>月27日</span><span style='font-size:10.5pt;'>到8月12日每日下午3点至午夜12点或凌晨1点。</span></span>&nbsp;<br><br><span style='font-size:24px;'><span style='font-size:10.5pt;'>五、工作福利</span></span></b>&nbsp;：活动结束后会评选优秀志愿者，并颁发证书。各类岗位工资见附件<br><br><span style='color:black;'>1</span><span style='color:black;'>、&nbsp;提供培训及工作期间的午餐或晚餐补助，每餐7元标准</span>&nbsp;<br><br><span style='color:black;'>2</span><span style='color:black;'>、提供统一着装</span>&nbsp;<br><br><span style='color:black;'>3</span><span style='color:black;'>、不提供住宿</span>&nbsp;<br><br><span style='color:black;'>4</span><span style='color:black;'>、<span style='background-color:yellow;'>可安排每日送车（不包括接的车，只是送车）</span></span>&nbsp;<br><br><span style='color:black;'>5</span><span style='color:black;'>、提供宣传海报<br></span><u><b><span style='color:black;'>请有意者自行下载报名表，填好后到北活F107报名咨询</span></b></u>",

        "time": "2013-11-3",
        "size":"4",        
        "tag": ""
    }
]
